responder3/__init__.py
responder3/__main__.py
responder3/core/__init__.py
responder3/core/asyncio_helpers.py
responder3/core/commons.py
responder3/core/gwss.py
responder3/core/rdns.py
responder3/core/responder3.py
responder3/core/servertask.py
responder3/core/servertemplate.py
responder3/core/sockets.py
responder3/core/ssl.py
responder3/core/test_helper.py
responder3/core/udpwrapper.py
responder3/core/__pycache__/__init__.cpython-37.pyc
responder3/core/__pycache__/asyncio_helpers.cpython-37.pyc
responder3/core/__pycache__/commons.cpython-37.pyc
responder3/core/__pycache__/gwss.cpython-37.pyc
responder3/core/__pycache__/rdns.cpython-37.pyc
responder3/core/__pycache__/responder3.cpython-37.pyc
responder3/core/__pycache__/servertask.cpython-37.pyc
responder3/core/__pycache__/servertemplate.cpython-37.pyc
responder3/core/__pycache__/sockets.cpython-37.pyc
responder3/core/__pycache__/ssl.cpython-37.pyc
responder3/core/__pycache__/udpwrapper.cpython-37.pyc
responder3/core/interfaces/NetworkInterface.py
responder3/core/interfaces/NetworkInterfaces.py
responder3/core/interfaces/README.md
responder3/core/interfaces/__init__.py
responder3/core/interfaces/darwin.py
responder3/core/interfaces/linux.py
responder3/core/interfaces/windows.py
responder3/core/interfaces/__pycache__/NetworkInterface.cpython-37.pyc
responder3/core/interfaces/__pycache__/NetworkInterfaces.cpython-37.pyc
responder3/core/interfaces/__pycache__/__init__.cpython-37.pyc
responder3/core/interfaces/__pycache__/darwin.cpython-37.pyc
responder3/core/interfaces/__pycache__/linux.cpython-37.pyc
responder3/core/interfaces/__pycache__/windows.cpython-37.pyc
responder3/core/logging/__init__.py
responder3/core/logging/log_objects.py
responder3/core/logging/logger.py
responder3/core/logging/logtask.py
responder3/core/logging/__pycache__/__init__.cpython-37.pyc
responder3/core/logging/__pycache__/log_objects.cpython-37.pyc
responder3/core/logging/__pycache__/logger.cpython-37.pyc
Responder3-0.0.1.dist-info/METADATA
Responder3-0.0.1.dist-info/WHEEL
Responder3-0.0.1.dist-info/entry_points.txt
Responder3-0.0.1.dist-info/top_level.txt
Responder3-0.0.1.dist-info/zip-safe
Responder3-0.0.1.dist-info/RECORD
